ctable/__init__.py
ctable/__main__.py
ctable/color.py
ctable/ctable.py
ctable/utils.py
ctable-0.0.4.dist-info/LICENSE
ctable-0.0.4.dist-info/METADATA
ctable-0.0.4.dist-info/WHEEL
ctable-0.0.4.dist-info/entry_points.txt
ctable-0.0.4.dist-info/top_level.txt
ctable-0.0.4.dist-info/RECORD
